ehrmonize/__init__.py
ehrmonize/ehrmonize.py
ehrmonize-0.1.2.dist-info/METADATA
ehrmonize-0.1.2.dist-info/WHEEL
ehrmonize-0.1.2.dist-info/licenses/LICENSE
ehrmonize-0.1.2.dist-info/RECORD
