Metadata-Version: 2.3
Name: ehrmonize
Version: 0.1.2
Summary: ehrmonize is package to abstract medical concepts using large language models.
Project-URL: homepage, https://github.com/aiwonglab/ehrmonize/
Project-URL: repository, https://github.com/aiwonglab/ehrmonize/
Project-URL: documentation, https://ehrmonize.readthedocs.io/
Author-email: João Matos <joao.matos@duke.edu>, "A. Ian Wong" <a.ian.wong@duke.edu>
License: MIT License
License-File: LICENSE
Keywords: AI,EHR,LLMs,ehrmonize,electronic health records,large language models,medical concept abstraction
Classifier: Development Status :: 3 - Alpha
Classifier: License :: OSI Approved :: MIT License
Classifier: Operating System :: OS Independent
Classifier: Programming Language :: Python :: 3
Requires-Python: >=3.9
Requires-Dist: boto3
Requires-Dist: numpy
Requires-Dist: openai
Requires-Dist: pandas
Requires-Dist: python-dotenv
Requires-Dist: tqdm
